{
  "exportedAt": "2026-05-26T14:20:31.776Z",
  "employees": [
    {
      "no": 2,
      "name": "鄭 基石",
      "kana": "ジョン キソク",
      "join": "2006-08-14",
      "birth": "1975-03-04",
      "kaigo": "auto",
      "koyo": "no",
      "shaho_start": "2011-08",
      "shotokuKbn": "ko",
      "fuyouCount": 0,
      "base": 0,
      "families": [],
      "commute": 0,
      "updatedAt": ""
    },
    {
      "no": 17,
      "name": "朴 娟慶",
      "kana": "パク  イョンギョン",
      "join": "2022-06-30",
      "birth": "1973-07-15",
      "kaigo": "auto",
      "koyo": "yes",
      "shaho_start": "2022-07",
      "shotokuKbn": "ko",
      "fuyouCount": 2,
      "base": 0,
      "families": [
        {
          "name": "イ　ダイン",
          "birth": "2004-04-12"
        },
        {
          "name": "イ　シウン",
          "birth": "2007-06-01"
        }
      ],
      "commute": 0,
      "updatedAt": ""
    },
    {
      "no": 19,
      "name": "朴 修完",
      "kana": "パク スワン",
      "join": "2025-02-06",
      "birth": "1991-03-20",
      "kaigo": "auto",
      "koyo": "yes",
      "shaho_start": "2025-04",
      "shotokuKbn": "ko",
      "fuyouCount": 0,
      "base": 0,
      "families": [],
      "commute": 0,
      "updatedAt": ""
    },
    {
      "no": 21,
      "name": "山本 まこと",
      "kana": "ヤマモト マコト",
      "join": "2025-04-30",
      "birth": "1997-06-02",
      "kaigo": "auto",
      "koyo": "yes",
      "shaho_start": "",
      "shotokuKbn": "ko",
      "fuyouCount": 1,
      "base": 0,
      "families": [
        {
          "name": "息子",
          "birth": "2005-03-03"
        },
        {
          "name": "娘",
          "birth": "2020-07-28"
        }
      ],
      "commute": 13500,
      "updatedAt": ""
    },
    {
      "no": 22,
      "name": "田中 一郎",
      "kana": "タナカ",
      "join": "2025-04-29",
      "birth": "1995-06-05",
      "kaigo": "auto",
      "koyo": "yes",
      "shaho_start": "",
      "shotokuKbn": "ko",
      "fuyouCount": 0,
      "base": 0,
      "families": [],
      "commute": 0,
      "updatedAt": ""
    },
    {
      "no": 23,
      "name": "홍길동",
      "kana": "홍길동",
      "join": "2025-03-04",
      "birth": "1999-12-30",
      "kaigo": "auto",
      "koyo": "yes",
      "shaho_start": "2026-04",
      "shotokuKbn": "ko",
      "fuyouCount": 0,
      "base": 0,
      "families": [],
      "commute": 0,
      "updatedAt": ""
    }
  ],
  "payrolls": [
    {
      "no": 2,
      "name": "鄭 基石",
      "year": 2024,
      "month": 12,
      "r-base": 200000,
      "r-ot": 0,
      "r-kintai": 0,
      "r-commute": 0,
      "r-commutetax": 0,
      "r-kinmu": 12200,
      "r-shokumu": 50000,
      "r-field": 0,
      "r-hyo": 0,
      "k-jumin": 5000,
      "k-nencho": -31280,
      "_net": 244076,
      "kenko": "",
      "nenkin": "",
      "shotoku": "",
      "totalPay": "",
      "totalKojo": "",
      "net": ""
    },
    {
      "no": 2,
      "name": "鄭 基石",
      "year": 2025,
      "month": 1,
      "r-base": 200000,
      "r-ot": 0,
      "r-kintai": 0,
      "r-commute": 0,
      "r-commutetax": 0,
      "r-kinmu": 12200,
      "r-shokumu": 50000,
      "r-field": 0,
      "r-hyo": 0,
      "k-jumin": 5000,
      "k-nencho": 0,
      "_net": 212796,
      "kenko": "",
      "nenkin": "",
      "shotoku": "",
      "totalPay": "",
      "totalKojo": "",
      "net": ""
    },
    {
      "no": 2,
      "name": "鄭 基石",
      "year": 2025,
      "month": 2,
      "r-base": 200000,
      "r-ot": 0,
      "r-kintai": 0,
      "r-commute": 0,
      "r-commutetax": 0,
      "r-kinmu": 12200,
      "r-shokumu": 50000,
      "r-field": 0,
      "r-hyo": 0,
      "k-jumin": 5000,
      "k-nencho": 0,
      "_net": 212796,
      "kenko": "",
      "nenkin": "",
      "shotoku": "",
      "totalPay": "",
      "totalKojo": "",
      "net": ""
    },
    {
      "no": 2,
      "name": "鄭 基石",
      "year": 2025,
      "month": 3,
      "r-base": 200000,
      "r-ot": 0,
      "r-kintai": 0,
      "r-commute": 0,
      "r-commutetax": 0,
      "r-kinmu": 12200,
      "r-shokumu": 50000,
      "r-field": 0,
      "r-hyo": 0,
      "k-jumin": 5000,
      "k-nencho": 0,
      "_net": 212900,
      "kenko": "",
      "nenkin": "",
      "shotoku": "",
      "totalPay": "",
      "totalKojo": "",
      "net": ""
    },
    {
      "no": 2,
      "name": "鄭 基石",
      "year": 2025,
      "month": 4,
      "r-base": 200000,
      "r-ot": 0,
      "r-kintai": 0,
      "r-commute": 0,
      "r-commutetax": 0,
      "r-kinmu": 12200,
      "r-shokumu": 50000,
      "r-field": 0,
      "r-hyo": 0,
      "k-jumin": 5000,
      "k-nencho": 0,
      "_net": 212900,
      "kenko": "",
      "nenkin": "",
      "shotoku": "",
      "totalPay": "",
      "totalKojo": "",
      "net": ""
    },
    {
      "no": 2,
      "name": "鄭 基石",
      "year": 2025,
      "month": 5,
      "r-base": 200000,
      "r-ot": 0,
      "r-kintai": 0,
      "r-commute": 0,
      "r-commutetax": 0,
      "r-kinmu": 12200,
      "r-shokumu": 50000,
      "r-field": 0,
      "r-hyo": 0,
      "k-jumin": 5000,
      "k-nencho": 0,
      "_net": 212900,
      "kenko": "",
      "nenkin": "",
      "shotoku": "",
      "totalPay": "",
      "totalKojo": "",
      "net": ""
    },
    {
      "no": 2,
      "name": "鄭 基石",
      "year": 2025,
      "month": 6,
      "r-base": 200000,
      "r-ot": 0,
      "r-kintai": 0,
      "r-commute": 0,
      "r-commutetax": 0,
      "r-kinmu": 12200,
      "r-shokumu": 50000,
      "r-field": 0,
      "r-hyo": 0,
      "k-jumin": 5000,
      "k-nencho": 0,
      "_net": 212900,
      "kenko": "",
      "nenkin": "",
      "shotoku": "",
      "totalPay": "",
      "totalKojo": "",
      "net": ""
    },
    {
      "no": 2,
      "name": "鄭 基石",
      "year": 2025,
      "month": 7,
      "r-base": 200000,
      "r-ot": 0,
      "r-kintai": 0,
      "r-commute": 0,
      "r-commutetax": 0,
      "r-kinmu": 12200,
      "r-shokumu": 50000,
      "r-field": 0,
      "r-hyo": 0,
      "k-jumin": 5000,
      "k-nencho": 0,
      "_net": 212900,
      "kenko": "",
      "nenkin": "",
      "shotoku": "",
      "totalPay": "",
      "totalKojo": "",
      "net": ""
    },
    {
      "no": 2,
      "name": "鄭 基石",
      "year": 2025,
      "month": 8,
      "r-base": 200000,
      "r-ot": 0,
      "r-kintai": 0,
      "r-commute": 0,
      "r-commutetax": 0,
      "r-kinmu": 12200,
      "r-shokumu": 50000,
      "r-field": 0,
      "r-hyo": 0,
      "k-jumin": 5000,
      "k-nencho": 0,
      "_net": 212900,
      "kenko": "",
      "nenkin": "",
      "shotoku": "",
      "totalPay": "",
      "totalKojo": "",
      "net": ""
    },
    {
      "no": 2,
      "name": "鄭 基石",
      "year": 2025,
      "month": 9,
      "r-base": 200000,
      "r-ot": 0,
      "r-kintai": 0,
      "r-commute": 0,
      "r-commutetax": 0,
      "r-kinmu": 0,
      "r-shokumu": 15000,
      "r-field": 0,
      "r-hyo": 260000,
      "k-jumin": 4900,
      "k-nencho": 0,
      "_net": 167450,
      "kenko": "",
      "nenkin": "",
      "shotoku": "",
      "totalPay": "",
      "totalKojo": "",
      "net": ""
    },
    {
      "no": 2,
      "name": "鄭 基石",
      "year": 2025,
      "month": 10,
      "r-base": 200000,
      "r-ot": 0,
      "r-kintai": 0,
      "r-commute": 0,
      "r-commutetax": 0,
      "r-kinmu": 0,
      "r-shokumu": 15000,
      "r-field": 0,
      "r-hyo": 260000,
      "k-jumin": 5300,
      "k-nencho": 0,
      "_net": 167050,
      "kenko": "",
      "nenkin": "",
      "shotoku": "",
      "totalPay": "",
      "totalKojo": "",
      "net": ""
    },
    {
      "no": 2,
      "name": "鄭 基石",
      "year": 2025,
      "month": 11,
      "r-base": 200000,
      "r-ot": 0,
      "r-kintai": 0,
      "r-commute": 0,
      "r-commutetax": 0,
      "r-kinmu": 0,
      "r-shokumu": 15000,
      "r-field": 0,
      "r-hyo": 0,
      "k-jumin": 4900,
      "k-nencho": 0,
      "_net": 173200,
      "kenko": "",
      "nenkin": "",
      "shotoku": "",
      "totalPay": "",
      "totalKojo": "",
      "net": ""
    },
    {
      "no": 2,
      "name": "鄭 基石",
      "year": 2025,
      "month": 12,
      "r-base": 200000,
      "r-ot": 28000,
      "r-kintai": 0,
      "r-commute": 0,
      "r-commutetax": 0,
      "r-kinmu": 0,
      "r-shokumu": 15000,
      "r-field": 0,
      "r-hyo": 220000,
      "k-jumin": 4900,
      "k-nencho": -61980,
      "_net": 262600,
      "kenko": "",
      "nenkin": "",
      "shotoku": "",
      "totalPay": "",
      "totalKojo": "",
      "net": ""
    },
    {
      "no": 2,
      "name": "鄭 基石",
      "year": 2026,
      "month": 1,
      "r-base": 200000,
      "r-ot": 26600,
      "r-kintai": 0,
      "r-commute": 0,
      "r-commutetax": 0,
      "r-kinmu": 0,
      "r-shokumu": 15000,
      "r-field": 0,
      "r-hyo": 220000,
      "k-jumin": 4900,
      "k-nencho": 0,
      "_net": 199290,
      "kenko": "",
      "nenkin": "",
      "shotoku": "",
      "totalPay": "",
      "totalKojo": "",
      "net": ""
    },
    {
      "no": 2,
      "name": "鄭 基石",
      "year": 2026,
      "month": 2,
      "r-base": 200000,
      "r-ot": 1400,
      "r-kintai": 0,
      "r-commute": 0,
      "r-commutetax": 0,
      "r-kinmu": 0,
      "r-shokumu": 15000,
      "r-field": 0,
      "r-hyo": 220000,
      "k-jumin": 4900,
      "k-nencho": 0,
      "_net": 174950,
      "kenko": "",
      "nenkin": "",
      "shotoku": "",
      "totalPay": "",
      "totalKojo": "",
      "net": ""
    },
    {
      "no": 2,
      "name": "鄭 基石",
      "year": 2026,
      "month": 3,
      "r-base": 200000,
      "r-ot": 37800,
      "r-kintai": 0,
      "r-commute": 0,
      "r-commutetax": 0,
      "r-kinmu": 0,
      "r-shokumu": 15000,
      "r-field": 0,
      "r-hyo": 220000,
      "k-jumin": 4900,
      "k-nencho": 0,
      "_net": 210103,
      "kenko": "",
      "nenkin": "",
      "shotoku": "",
      "totalPay": "",
      "totalKojo": "",
      "net": ""
    },
    {
      "no": 2,
      "name": "鄭 基石",
      "year": 2026,
      "month": 4,
      "r-base": 200000,
      "r-ot": 2800,
      "r-kintai": 0,
      "r-commute": 0,
      "r-commutetax": 0,
      "r-kinmu": 0,
      "r-shokumu": 15000,
      "r-field": 0,
      "r-hyo": 220000,
      "k-jumin": 4900,
      "k-nencho": 0,
      "_net": 176130,
      "kenko": "",
      "nenkin": "",
      "shotoku": "",
      "totalPay": "",
      "totalKojo": "",
      "net": ""
    },
    {
      "no": 2,
      "name": "鄭 基石",
      "year": 2026,
      "month": 5,
      "r-base": "",
      "r-ot": "",
      "r-kintai": "",
      "r-commute": "",
      "r-commutetax": "",
      "r-kinmu": "",
      "r-shokumu": "",
      "r-field": "",
      "k-jumin": "",
      "k-nencho": "",
      "kenko": 10835,
      "kaigo": "",
      "kodomo": "",
      "nenkin": 20130,
      "koyo": "",
      "shotoku": 3770,
      "net": 176130,
      "updatedAt": "2026-05-20T09:25:19.402Z"
    },
    {
      "no": 17,
      "name": "朴 娟慶",
      "year": 2024,
      "month": 12,
      "r-base": 360000,
      "r-ot": 0,
      "r-kintai": 0,
      "r-commute": 0,
      "r-commutetax": 0,
      "r-kinmu": 0,
      "r-shokumu": 0,
      "r-field": 0,
      "r-hyo": 0,
      "k-jumin": 6400,
      "k-nencho": -21000,
      "_net": 313406,
      "kenko": "",
      "nenkin": "",
      "shotoku": "",
      "totalPay": "",
      "totalKojo": "",
      "net": ""
    },
    {
      "no": 17,
      "name": "朴 娟慶",
      "year": 2025,
      "month": 1,
      "r-base": 360000,
      "r-ot": 0,
      "r-kintai": 0,
      "r-commute": 0,
      "r-commutetax": 0,
      "r-kinmu": 0,
      "r-shokumu": 0,
      "r-field": 0,
      "r-hyo": 0,
      "k-jumin": 6400,
      "k-nencho": 0,
      "_net": 292406,
      "kenko": "",
      "nenkin": "",
      "shotoku": "",
      "totalPay": "",
      "totalKojo": "",
      "net": ""
    },
    {
      "no": 17,
      "name": "朴 娟慶",
      "year": 2025,
      "month": 2,
      "r-base": 360000,
      "r-ot": 0,
      "r-kintai": 0,
      "r-commute": 0,
      "r-commutetax": 0,
      "r-kinmu": 0,
      "r-shokumu": 0,
      "r-field": 0,
      "r-hyo": 0,
      "k-jumin": 6400,
      "k-nencho": 0,
      "_net": 292406,
      "kenko": "",
      "nenkin": "",
      "shotoku": "",
      "totalPay": "",
      "totalKojo": "",
      "net": ""
    },
    {
      "no": 17,
      "name": "朴 娟慶",
      "year": 2025,
      "month": 3,
      "r-base": 360000,
      "r-ot": 0,
      "r-kintai": 0,
      "r-commute": 0,
      "r-commutetax": 0,
      "r-kinmu": 0,
      "r-shokumu": 0,
      "r-field": 0,
      "r-hyo": 0,
      "k-jumin": 6400,
      "k-nencho": 0,
      "_net": 292550,
      "kenko": "",
      "nenkin": "",
      "shotoku": "",
      "totalPay": "",
      "totalKojo": "",
      "net": ""
    },
    {
      "no": 17,
      "name": "朴 娟慶",
      "year": 2025,
      "month": 4,
      "r-base": 360000,
      "r-ot": 0,
      "r-kintai": 0,
      "r-commute": 0,
      "r-commutetax": 0,
      "r-kinmu": 0,
      "r-shokumu": 0,
      "r-field": 0,
      "r-hyo": 0,
      "k-jumin": 6400,
      "k-nencho": 0,
      "_net": 292730,
      "kenko": "",
      "nenkin": "",
      "shotoku": "",
      "totalPay": "",
      "totalKojo": "",
      "net": ""
    },
    {
      "no": 17,
      "name": "朴 娟慶",
      "year": 2025,
      "month": 5,
      "r-base": 360000,
      "r-ot": 0,
      "r-kintai": 0,
      "r-commute": 0,
      "r-commutetax": 0,
      "r-kinmu": 0,
      "r-shokumu": 0,
      "r-field": 0,
      "r-hyo": 0,
      "k-jumin": 6400,
      "k-nencho": 0,
      "_net": 292730,
      "kenko": "",
      "nenkin": "",
      "shotoku": "",
      "totalPay": "",
      "totalKojo": "",
      "net": ""
    },
    {
      "no": 17,
      "name": "朴 娟慶",
      "year": 2025,
      "month": 6,
      "r-base": 360000,
      "r-ot": 0,
      "r-kintai": 0,
      "r-commute": 0,
      "r-commutetax": 0,
      "r-kinmu": 0,
      "r-shokumu": 0,
      "r-field": 0,
      "r-hyo": 0,
      "k-jumin": 6400,
      "k-nencho": 0,
      "_net": 292730,
      "kenko": "",
      "nenkin": "",
      "shotoku": "",
      "totalPay": "",
      "totalKojo": "",
      "net": ""
    },
    {
      "no": 17,
      "name": "朴 娟慶",
      "year": 2025,
      "month": 7,
      "r-base": 360000,
      "r-ot": 0,
      "r-kintai": 0,
      "r-commute": 0,
      "r-commutetax": 0,
      "r-kinmu": 0,
      "r-shokumu": 0,
      "r-field": 0,
      "r-hyo": 0,
      "k-jumin": 6400,
      "k-nencho": 0,
      "_net": 292730,
      "kenko": "",
      "nenkin": "",
      "shotoku": "",
      "totalPay": "",
      "totalKojo": "",
      "net": ""
    },
    {
      "no": 17,
      "name": "朴 娟慶",
      "year": 2025,
      "month": 8,
      "r-base": 360000,
      "r-ot": 0,
      "r-kintai": 0,
      "r-commute": 0,
      "r-commutetax": 0,
      "r-kinmu": 0,
      "r-shokumu": 0,
      "r-field": 0,
      "r-hyo": 0,
      "k-jumin": 6400,
      "k-nencho": 0,
      "_net": 292730,
      "kenko": "",
      "nenkin": "",
      "shotoku": "",
      "totalPay": "",
      "totalKojo": "",
      "net": ""
    },
    {
      "no": 17,
      "name": "朴 娟慶",
      "year": 2025,
      "month": 9,
      "r-base": 360000,
      "r-ot": 0,
      "r-kintai": 0,
      "r-commute": 0,
      "r-commutetax": 0,
      "r-kinmu": 0,
      "r-shokumu": 0,
      "r-field": 0,
      "r-hyo": 0,
      "k-jumin": 6700,
      "k-nencho": 0,
      "_net": 292430,
      "kenko": "",
      "nenkin": "",
      "shotoku": "",
      "totalPay": "",
      "totalKojo": "",
      "net": ""
    },
    {
      "no": 17,
      "name": "朴 娟慶",
      "year": 2025,
      "month": 10,
      "r-base": 360000,
      "r-ot": 0,
      "r-kintai": 0,
      "r-commute": 0,
      "r-commutetax": 0,
      "r-kinmu": 0,
      "r-shokumu": 0,
      "r-field": 0,
      "r-hyo": 0,
      "k-jumin": 8200,
      "k-nencho": 0,
      "_net": 290930,
      "kenko": "",
      "nenkin": "",
      "shotoku": "",
      "totalPay": "",
      "totalKojo": "",
      "net": ""
    },
    {
      "no": 17,
      "name": "朴 娟慶",
      "year": 2025,
      "month": 11,
      "r-base": 360000,
      "r-ot": 0,
      "r-kintai": 0,
      "r-commute": 0,
      "r-commutetax": 0,
      "r-kinmu": 0,
      "r-shokumu": 0,
      "r-field": 0,
      "r-hyo": 0,
      "k-jumin": 6700,
      "k-nencho": 0,
      "_net": 292430,
      "kenko": "",
      "nenkin": "",
      "shotoku": "",
      "totalPay": "",
      "totalKojo": "",
      "net": ""
    },
    {
      "no": 17,
      "name": "朴 娟慶",
      "year": 2025,
      "month": 12,
      "r-base": 360000,
      "r-ot": 0,
      "r-kintai": 0,
      "r-commute": 0,
      "r-commutetax": 0,
      "r-kinmu": 0,
      "r-shokumu": 0,
      "r-field": 0,
      "r-hyo": 360000,
      "k-jumin": 6700,
      "k-nencho": -39700,
      "_net": 332560,
      "kenko": "",
      "nenkin": "",
      "shotoku": "",
      "totalPay": "",
      "totalKojo": "",
      "net": ""
    },
    {
      "no": 17,
      "name": "朴 娟慶",
      "year": 2026,
      "month": 1,
      "r-base": 360000,
      "r-ot": 0,
      "r-kintai": 0,
      "r-commute": 0,
      "r-commutetax": 0,
      "r-kinmu": 0,
      "r-shokumu": 0,
      "r-field": 0,
      "r-hyo": 360000,
      "k-jumin": 6700,
      "k-nencho": 0,
      "_net": 292860,
      "kenko": "",
      "nenkin": "",
      "shotoku": "",
      "totalPay": "",
      "totalKojo": "",
      "net": ""
    },
    {
      "no": 17,
      "name": "朴 娟慶",
      "year": 2026,
      "month": 2,
      "r-base": 360000,
      "r-ot": 0,
      "r-kintai": 0,
      "r-commute": 0,
      "r-commutetax": 0,
      "r-kinmu": 0,
      "r-shokumu": 0,
      "r-field": 0,
      "r-hyo": 360000,
      "k-jumin": 6700,
      "k-nencho": 0,
      "_net": 292860,
      "kenko": "",
      "nenkin": "",
      "shotoku": "",
      "totalPay": "",
      "totalKojo": "",
      "net": ""
    },
    {
      "no": 17,
      "name": "朴 娟慶",
      "year": 2026,
      "month": 3,
      "r-base": 360000,
      "r-ot": 0,
      "r-kintai": 0,
      "r-commute": 0,
      "r-commutetax": 0,
      "r-kinmu": 0,
      "r-shokumu": 0,
      "r-field": 0,
      "r-hyo": 360000,
      "k-jumin": 6700,
      "k-nencho": 0,
      "_net": 292914,
      "kenko": "",
      "nenkin": "",
      "shotoku": "",
      "totalPay": "",
      "totalKojo": "",
      "net": ""
    },
    {
      "no": 17,
      "name": "朴 娟慶",
      "year": 2026,
      "month": 4,
      "r-base": 360000,
      "r-ot": 0,
      "r-kintai": 0,
      "r-commute": 0,
      "r-commutetax": 0,
      "r-kinmu": 0,
      "r-shokumu": 0,
      "r-field": 0,
      "r-hyo": 360000,
      "k-jumin": 6700,
      "k-nencho": 0,
      "_net": 292680,
      "kenko": "",
      "nenkin": "",
      "shotoku": "",
      "totalPay": "",
      "totalKojo": "",
      "net": ""
    },
    {
      "no": 17,
      "name": "朴 娟慶",
      "year": 2026,
      "month": 5,
      "r-commutetax": 0,
      "k-nencho": 0,
      "r-ot": 0,
      "r-base": 360000,
      "r-commute": 0,
      "r-field": 0,
      "r-kinmu": 0,
      "k-jumin": 6700,
      "_net": 292680,
      "r-kintai": 0,
      "r-shokumu": 0,
      "kenko": 17730,
      "kaigo": "",
      "kodomo": "",
      "nenkin": 32940,
      "koyo": "",
      "shotoku": 8040,
      "net": 289460,
      "updatedAt": "2026-05-20T09:25:47.308Z"
    },
    {
      "no": 19,
      "name": "朴 修完",
      "year": 2025,
      "month": 1,
      "r-base": 0,
      "r-ot": 0,
      "r-kintai": 0,
      "r-commute": 0,
      "r-commutetax": 0,
      "r-kinmu": 0,
      "r-shokumu": 0,
      "r-field": 0,
      "r-hyo": 0,
      "k-jumin": 0,
      "k-nencho": 0,
      "_net": 0
    },
    {
      "no": 19,
      "name": "朴 修完",
      "year": 2025,
      "month": 2,
      "r-base": 136000,
      "r-ot": 5000,
      "r-kintai": 0,
      "r-commute": 2880,
      "r-commutetax": 0,
      "r-kinmu": 68000,
      "r-shokumu": 0,
      "r-field": 0,
      "r-hyo": 0,
      "k-jumin": 0,
      "k-nencho": 0,
      "_net": 206750,
      "kenko": "",
      "nenkin": "",
      "shotoku": "",
      "totalPay": "",
      "totalKojo": "",
      "net": ""
    },
    {
      "no": 19,
      "name": "朴 修完",
      "year": 2025,
      "month": 3,
      "r-base": 200000,
      "r-ot": 20400,
      "r-kintai": 0,
      "r-commute": 13150,
      "r-commutetax": 0,
      "r-kinmu": 100000,
      "r-shokumu": 0,
      "r-field": 0,
      "r-hyo": 0,
      "k-jumin": 0,
      "k-nencho": 0,
      "_net": 323410,
      "kenko": "",
      "nenkin": "",
      "shotoku": "",
      "totalPay": "",
      "totalKojo": "",
      "net": ""
    },
    {
      "no": 19,
      "name": "朴 修完",
      "year": 2025,
      "month": 4,
      "r-base": 200000,
      "r-ot": 3600,
      "r-kintai": 0,
      "r-commute": 13150,
      "r-commutetax": 0,
      "r-kinmu": 100000,
      "r-shokumu": 0,
      "r-field": 0,
      "r-hyo": 300000,
      "k-jumin": 0,
      "k-nencho": 0,
      "_net": 265843,
      "kenko": "",
      "nenkin": "",
      "shotoku": "",
      "totalPay": "",
      "totalKojo": "",
      "net": ""
    },
    {
      "no": 19,
      "name": "朴 修完",
      "year": 2025,
      "month": 5,
      "r-base": 200000,
      "r-ot": 7200,
      "r-kintai": 0,
      "r-commute": 13150,
      "r-commutetax": 0,
      "r-kinmu": 100000,
      "r-shokumu": 0,
      "r-field": 0,
      "r-hyo": 300000,
      "k-jumin": 0,
      "k-nencho": 0,
      "_net": 269203,
      "kenko": "",
      "nenkin": "",
      "shotoku": "",
      "totalPay": "",
      "totalKojo": "",
      "net": ""
    },
    {
      "no": 19,
      "name": "朴 修完",
      "year": 2025,
      "month": 6,
      "r-base": 200000,
      "r-ot": 10800,
      "r-kintai": 0,
      "r-commute": 13150,
      "r-commutetax": 0,
      "r-kinmu": 100000,
      "r-shokumu": 0,
      "r-field": 0,
      "r-hyo": 300000,
      "k-jumin": 0,
      "k-nencho": 0,
      "_net": 272673,
      "kenko": "",
      "nenkin": "",
      "shotoku": "",
      "totalPay": "",
      "totalKojo": "",
      "net": ""
    },
    {
      "no": 19,
      "name": "朴 修完",
      "year": 2025,
      "month": 7,
      "r-base": 200000,
      "r-ot": 12000,
      "r-kintai": 0,
      "r-commute": 13150,
      "r-commutetax": 0,
      "r-kinmu": 100000,
      "r-shokumu": 0,
      "r-field": 0,
      "r-hyo": 300000,
      "k-jumin": 0,
      "k-nencho": 0,
      "_net": 273867,
      "kenko": "",
      "nenkin": "",
      "shotoku": "",
      "totalPay": "",
      "totalKojo": "",
      "net": ""
    },
    {
      "no": 19,
      "name": "朴 修完",
      "year": 2025,
      "month": 8,
      "r-base": 200000,
      "r-ot": 15600,
      "r-kintai": 0,
      "r-commute": 13150,
      "r-commutetax": 0,
      "r-kinmu": 100000,
      "r-shokumu": 0,
      "r-field": 0,
      "r-hyo": 300000,
      "k-jumin": 0,
      "k-nencho": 0,
      "_net": 277347,
      "kenko": "",
      "nenkin": "",
      "shotoku": "",
      "totalPay": "",
      "totalKojo": "",
      "net": ""
    },
    {
      "no": 19,
      "name": "朴 修完",
      "year": 2025,
      "month": 9,
      "r-base": 200000,
      "r-ot": 19200,
      "r-kintai": 0,
      "r-commute": 13150,
      "r-commutetax": 0,
      "r-kinmu": 100000,
      "r-shokumu": 0,
      "r-field": 0,
      "r-hyo": 300000,
      "k-jumin": 0,
      "k-nencho": 0,
      "_net": 280717,
      "kenko": "",
      "nenkin": "",
      "shotoku": "",
      "totalPay": "",
      "totalKojo": "",
      "net": ""
    },
    {
      "no": 19,
      "name": "朴 修完",
      "year": 2025,
      "month": 10,
      "r-base": 200000,
      "r-ot": 20000,
      "r-kintai": 0,
      "r-commute": 13150,
      "r-commutetax": 0,
      "r-kinmu": 100000,
      "r-shokumu": 0,
      "r-field": 0,
      "r-hyo": 300000,
      "k-jumin": 0,
      "k-nencho": 0,
      "_net": 281513,
      "kenko": "",
      "nenkin": "",
      "shotoku": "",
      "totalPay": "",
      "totalKojo": "",
      "net": ""
    },
    {
      "no": 19,
      "name": "朴 修完",
      "year": 2025,
      "month": 11,
      "r-base": 200000,
      "r-ot": 0,
      "r-kintai": 0,
      "r-commute": 13150,
      "r-commutetax": 0,
      "r-kinmu": 100000,
      "r-shokumu": 0,
      "r-field": 0,
      "r-hyo": 300000,
      "k-jumin": 0,
      "k-nencho": 0,
      "_net": 262363,
      "kenko": "",
      "nenkin": "",
      "shotoku": "",
      "totalPay": "",
      "totalKojo": "",
      "net": ""
    },
    {
      "no": 19,
      "name": "朴 修完",
      "year": 2025,
      "month": 12,
      "r-base": 200000,
      "r-ot": 47500,
      "r-kintai": 0,
      "r-commute": 13150,
      "r-commutetax": 0,
      "r-kinmu": 100000,
      "r-shokumu": 0,
      "r-field": 0,
      "r-hyo": 300000,
      "k-jumin": 0,
      "k-nencho": -31860,
      "_net": 340151,
      "kenko": "",
      "nenkin": "",
      "shotoku": "",
      "totalPay": "",
      "totalKojo": "",
      "net": ""
    },
    {
      "no": 19,
      "name": "朴 修完",
      "year": 2026,
      "month": 1,
      "r-base": 200000,
      "r-ot": 12500,
      "r-kintai": 0,
      "r-commute": 13150,
      "r-commutetax": 0,
      "r-kinmu": 100000,
      "r-shokumu": 0,
      "r-field": 0,
      "r-hyo": 300000,
      "k-jumin": 0,
      "k-nencho": 0,
      "_net": 274794,
      "kenko": "",
      "nenkin": "",
      "shotoku": "",
      "totalPay": "",
      "totalKojo": "",
      "net": ""
    },
    {
      "no": 19,
      "name": "朴 修完",
      "year": 2026,
      "month": 2,
      "r-base": 200000,
      "r-ot": 2500,
      "r-kintai": 0,
      "r-commute": 13150,
      "r-commutetax": 0,
      "r-kinmu": 100000,
      "r-shokumu": 0,
      "r-field": 0,
      "r-hyo": 300000,
      "k-jumin": 0,
      "k-nencho": 0,
      "_net": 265169,
      "kenko": "",
      "nenkin": "",
      "shotoku": "",
      "totalPay": "",
      "totalKojo": "",
      "net": ""
    },
    {
      "no": 19,
      "name": "朴 修完",
      "year": 2026,
      "month": 3,
      "r-base": 200000,
      "r-ot": 80000,
      "r-kintai": 0,
      "r-commute": 13150,
      "r-commutetax": 0,
      "r-kinmu": 100000,
      "r-shokumu": 0,
      "r-field": 0,
      "r-hyo": 300000,
      "k-jumin": 0,
      "k-nencho": 0,
      "_net": 338253,
      "kenko": "",
      "nenkin": "",
      "shotoku": "",
      "totalPay": "",
      "totalKojo": "",
      "net": ""
    },
    {
      "no": 19,
      "name": "朴 修完",
      "year": 2026,
      "month": 4,
      "r-base": 200000,
      "r-ot": 1250,
      "r-kintai": 0,
      "r-commute": 21930,
      "r-commutetax": 0,
      "r-kinmu": 100000,
      "r-shokumu": 8333,
      "r-field": 0,
      "r-hyo": 320000,
      "k-jumin": 0,
      "k-nencho": 0,
      "_net": 277917,
      "kenko": "",
      "nenkin": "",
      "shotoku": "",
      "totalPay": "",
      "totalKojo": "",
      "net": ""
    },
    {
      "no": 19,
      "name": "朴 修完",
      "year": 2026,
      "month": 5,
      "r-commutetax": 0,
      "k-nencho": 0,
      "r-ot": 1250,
      "r-base": 200000,
      "r-commute": 21930,
      "r-field": 0,
      "r-kinmu": 100000,
      "k-jumin": 0,
      "_net": 277917,
      "r-kintai": 0,
      "r-shokumu": 8333,
      "kenko": 16745,
      "kaigo": "",
      "kodomo": "",
      "nenkin": 31110,
      "koyo": "",
      "shotoku": 6420,
      "net": 273946,
      "updatedAt": "2026-05-20T09:25:50.159Z"
    },
    {
      "no": 22,
      "name": "田中 一郎",
      "year": 2026,
      "month": 4,
      "r-base": "",
      "r-ot": "",
      "r-kintai": "",
      "r-commute": "",
      "r-commutetax": "",
      "r-kinmu": "",
      "r-shokumu": "",
      "r-field": "",
      "r-hyo": "",
      "k-jumin": "",
      "k-nencho": "",
      "_net": "",
      "kenko": 4826,
      "nenkin": 8967,
      "shotoku": 1710,
      "totalPay": 150000,
      "totalKojo": 16365,
      "net": 133635
    },
    {
      "no": 22,
      "name": "田中 一郎",
      "year": 2026,
      "month": 5,
      "r-base": "",
      "r-ot": "",
      "r-kintai": "",
      "r-commute": "",
      "r-commutetax": "",
      "r-kinmu": "",
      "r-shokumu": "",
      "r-field": "",
      "r-hyo": "",
      "k-jumin": "",
      "k-nencho": "",
      "_net": "",
      "kenko": 4826,
      "nenkin": 8967,
      "shotoku": 1710,
      "totalPay": 150000,
      "totalKojo": 16365,
      "net": 133635
    },
    {
      "no": 23,
      "name": "홍길동",
      "year": 2026,
      "month": 3,
      "r-base": "",
      "r-ot": "",
      "r-kintai": "",
      "r-commute": "",
      "r-commutetax": "",
      "r-kinmu": "",
      "r-shokumu": "",
      "r-field": "",
      "r-hyo": "",
      "k-jumin": "",
      "k-nencho": "",
      "_net": "",
      "kenko": 0,
      "nenkin": 0,
      "shotoku": 0,
      "totalPay": 0,
      "totalKojo": 0,
      "net": 0
    },
    {
      "no": 23,
      "name": "홍길동",
      "year": 2026,
      "month": 4,
      "r-base": "",
      "r-ot": "",
      "r-kintai": "",
      "r-commute": "",
      "r-commutetax": "",
      "r-kinmu": "",
      "r-shokumu": "",
      "r-field": "",
      "r-hyo": "",
      "k-jumin": "",
      "k-nencho": "",
      "_net": "",
      "kenko": 9850,
      "nenkin": 18300,
      "shotoku": 4340,
      "totalPay": 230000,
      "totalKojo": 33870,
      "net": 196130
    },
    {
      "no": 23,
      "name": "홍길동",
      "year": 2026,
      "month": 5,
      "r-base": "",
      "r-ot": "",
      "r-kintai": "",
      "r-commute": "",
      "r-commutetax": "",
      "r-kinmu": "",
      "r-shokumu": "",
      "r-field": "",
      "r-hyo": "",
      "k-jumin": "",
      "k-nencho": "",
      "_net": "",
      "kenko": 9850,
      "nenkin": 18300,
      "shotoku": 3270,
      "totalPay": 200000,
      "totalKojo": 32650,
      "net": 167350
    }
  ],
  "rateHistory": [
    {
      "from": "2024-03",
      "kenko": 9.98,
      "kaigo": 1.6,
      "kodomo": 0,
      "nenkin": 18.3,
      "koyo": 0.6
    },
    {
      "from": "2024-04",
      "kenko": 9.98,
      "kaigo": 1.6,
      "kodomo": 0,
      "nenkin": 18.3,
      "koyo": 0.6
    },
    {
      "from": "2025-03",
      "kenko": 9.91,
      "kaigo": 1.59,
      "kodomo": 0,
      "nenkin": 18.3,
      "koyo": 0.6
    },
    {
      "from": "2025-04",
      "kenko": 9.91,
      "kaigo": 1.59,
      "kodomo": 0,
      "nenkin": 18.3,
      "koyo": 0.55
    },
    {
      "from": "2026-03",
      "kenko": 9.85,
      "kaigo": 1.62,
      "kodomo": 0,
      "nenkin": 18.3,
      "koyo": 0.55
    },
    {
      "from": "2026-04",
      "kenko": 9.85,
      "kaigo": 1.62,
      "kodomo": 0.23,
      "nenkin": 18.3,
      "koyo": 0.5
    }
  ]
}